{
  "common": {
    "text": {
      "home": "หน้าแรก",
      "about": "เกี่ยวกับเรา",
      "news": "ข่าวสาร",
      "contact": "ช่องทางการติดต่อ",
      "back": "กลับ",
      "copyright": "© ลิขสิทธิ์ 2024 Venoxity. สงวนลิขสิทธิ์.",
      "privacy": "นโยบายความเป็นส่วนตัว",
      "terms": "เงื่อนไขการใช้งาน",
      "documentation": "เอกสารกำกับ",
      "support": "ช่วยเหลือ",
      "workInProgress": "กำลังพัฒนา",
      "goToMainPage": "ไปที่หน้าหลัก",
      "pageNotFound": "ไม่พบหน้านี้",
      "motto": " Vigilance Unleashed, Where the Hawk's Gaze Never Wavers"
    }
  }
}
